datcat/__init__.py
datcat/adapters/__init__.py
datcat/adapters/repository.py
datcat/domain/__init__.py
datcat/domain/model.py
datcat/domain/types.py
datcat/entrypoints/__init__.py
datcat/entrypoints/app.py
datcat/entrypoints/flask_app.py
datcat/service_layer/__init__.py
datcat/service_layer/mappings.py
datcat/settings.py
datcat-0.1.4.dist-info/entry_points.txt
datcat-0.1.4.dist-info/WHEEL
datcat-0.1.4.dist-info/METADATA
datcat-0.1.4.dist-info/RECORD
