Metadata-Version: 2.1
Name: datcat
Version: 0.1.4
Summary: Simple Data Catalogue API
Home-page: https://github.com/antonio-one/datcat
License: TBC
Keywords: python,fastapi,data,catalogue,api
Author: Antonio
Author-email: antonio.one@pm.me
Requires-Python: >=3.8,<4.0
Classifier: License :: Other/Proprietary License
Classifier: Programming Language :: Python :: 3
Classifier: Programming Language :: Python :: 3.8
Classifier: Programming Language :: Python :: 3.9
Requires-Dist: Flask (>=1.1.2,<2.0.0)
Requires-Dist: Flask-API (>=2.0,<3.0)
Requires-Dist: fastapi (>=0.63.0,<0.64.0)
Requires-Dist: python-decouple (>=3.4,<4.0)
Requires-Dist: requests (>=2.25.1,<3.0.0)
Requires-Dist: uvicorn (>=0.13.4,<0.14.0)
Project-URL: Repository, https://github.com/antonio-one/datcat
